[
  {
    "word": "water",
    "category": "Noun",
    "marathi": {
      "script": "पाणी",
      "transliteration": "paani"
    },
    "level": "Beginner",
    "emoji": "💧"
  },
  {
    "word": "food",
    "category": "Noun",
    "marathi": {
      "script": "अन्न",
      "transliteration": "anna"
    },
    "level": "Beginner",
    "emoji": "🍽️"
  },
  {
    "word": "house",
    "category": "Noun",
    "marathi": {
      "script": "घर",
      "transliteration": "ghar"
    },
    "level": "Beginner",
    "emoji": "🏠"
  },
  {
    "word": "man",
    "category": "Noun",
    "marathi": {
      "script": "माणूस",
      "transliteration": "maanus"
    },
    "level": "Beginner",
    "emoji": "👨"
  },
  {
    "word": "woman",
    "category": "Noun",
    "marathi": {
      "script": "स्त्री",
      "transliteration": "stree"
    },
    "level": "Beginner",
    "emoji": "👩"
  },
  {
    "word": "child",
    "category": "Noun",
    "marathi": {
      "script": "मुल",
      "transliteration": "mul"
    },
    "level": "Beginner",
    "emoji": "🧒"
  },
  {
    "word": "I",
    "category": "Pronoun",
    "marathi": {
      "script": "मी",
      "transliteration": "mee"
    },
    "level": "Beginner",
    "emoji": "👤"
  },
  {
    "word": "you",
    "category": "Pronoun",
    "marathi": {
      "script": "तू",
      "transliteration": "too"
    },
    "level": "Beginner",
    "emoji": "👉"
  },
  {
    "word": "he",
    "category": "Pronoun",
    "marathi": {
      "script": "तो",
      "transliteration": "to"
    },
    "level": "Beginner",
    "emoji": "👨"
  },
  {
    "word": "she",
    "category": "Pronoun",
    "marathi": {
      "script": "ती",
      "transliteration": "tee"
    },
    "level": "Beginner",
    "emoji": "👩"
  },
  {
    "word": "we",
    "category": "Pronoun",
    "marathi": {
      "script": "आम्ही",
      "transliteration": "aamhi"
    },
    "level": "Beginner",
    "emoji": "👥"
  },
  {
    "word": "this",
    "category": "Pronoun",
    "marathi": {
      "script": "हे",
      "transliteration": "he"
    },
    "level": "Beginner",
    "emoji": "👇"
  },
  {
    "word": "that",
    "category": "Pronoun",
    "marathi": {
      "script": "ते",
      "transliteration": "te"
    },
    "level": "Beginner",
    "emoji": "👉"
  },
  {
    "word": "eat",
    "category": "Verb",
    "marathi": {
      "script": "खाणे",
      "transliteration": "khane"
    },
    "level": "Beginner",
    "emoji": "🍔"
  },
  {
    "word": "drink",
    "category": "Verb",
    "marathi": {
      "script": "पिणे",
      "transliteration": "pine"
    },
    "level": "Beginner",
    "emoji": "🥤"
  },
  {
    "word": "go",
    "category": "Verb",
    "marathi": {
      "script": "जाणे",
      "transliteration": "jaane"
    },
    "level": "Beginner",
    "emoji": "🚶"
  },
  {
    "word": "come",
    "category": "Verb",
    "marathi": {
      "script": "येणे",
      "transliteration": "yene"
    },
    "level": "Beginner",
    "emoji": "🏃"
  },
  {
    "word": "see",
    "category": "Verb",
    "marathi": {
      "script": "पाहणे",
      "transliteration": "pahane"
    },
    "level": "Beginner",
    "emoji": "👀"
  },
  {
    "word": "speak",
    "category": "Verb",
    "marathi": {
      "script": "बोलणे",
      "transliteration": "bolane"
    },
    "level": "Beginner",
    "emoji": "🗣️"
  },
  {
    "word": "do",
    "category": "Verb",
    "marathi": {
      "script": "करणे",
      "transliteration": "karane"
    },
    "level": "Beginner",
    "emoji": "🛠️"
  },
  {
    "word": "big",
    "category": "Adjective",
    "marathi": {
      "script": "मोठा",
      "transliteration": "motha"
    },
    "level": "Beginner",
    "emoji": "🐘"
  },
  {
    "word": "small",
    "category": "Adjective",
    "marathi": {
      "script": "लहान",
      "transliteration": "lahan"
    },
    "level": "Beginner",
    "emoji": "🐁"
  },
  {
    "word": "good",
    "category": "Adjective",
    "marathi": {
      "script": "चांगला",
      "transliteration": "changla"
    },
    "level": "Beginner",
    "emoji": "👍"
  },
  {
    "word": "bad",
    "category": "Adjective",
    "marathi": {
      "script": "वाईट",
      "transliteration": "vaait"
    },
    "level": "Beginner",
    "emoji": "👎"
  },
  {
    "word": "yes",
    "category": "Other",
    "marathi": {
      "script": "हो",
      "transliteration": "ho"
    },
    "level": "Beginner",
    "emoji": "✔️"
  },
  {
    "word": "no",
    "category": "Other",
    "marathi": {
      "script": "नाही",
      "transliteration": "naahi"
    },
    "level": "Beginner",
    "emoji": "❌"
  },
  {
    "word": "school",
    "category": "Noun",
    "marathi": {
      "script": "शाळा",
      "transliteration": "shaala"
    },
    "level": "Intermediate",
    "emoji": "🏫"
  },
  {
    "word": "book",
    "category": "Noun",
    "marathi": {
      "script": "पुस्तक",
      "transliteration": "pustak"
    },
    "level": "Intermediate",
    "emoji": "📖"
  },
  {
    "word": "friend",
    "category": "Noun",
    "marathi": {
      "script": "मित्र",
      "transliteration": "mitra"
    },
    "level": "Intermediate",
    "emoji": "🤝"
  },
  {
    "word": "family",
    "category": "Noun",
    "marathi": {
      "script": "कुटुंब",
      "transliteration": "kutumb"
    },
    "level": "Intermediate",
    "emoji": "👨‍👩‍👧‍👦"
  },
  {
    "word": "time",
    "category": "Noun",
    "marathi": {
      "script": "वेळ",
      "transliteration": "vel"
    },
    "level": "Intermediate",
    "emoji": "⏱️"
  },
  {
    "word": "day",
    "category": "Noun",
    "marathi": {
      "script": "दिवस",
      "transliteration": "divas"
    },
    "level": "Intermediate",
    "emoji": "☀️"
  },
  {
    "word": "today",
    "category": "Noun",
    "marathi": {
      "script": "आज",
      "transliteration": "aaj"
    },
    "level": "Intermediate",
    "emoji": "📅"
  },
  {
    "word": "tomorrow",
    "category": "Noun",
    "marathi": {
      "script": "उद्या",
      "transliteration": "udya"
    },
    "level": "Intermediate",
    "emoji": "⏭️"
  },
  {
    "word": "yesterday",
    "category": "Noun",
    "marathi": {
      "script": "काल",
      "transliteration": "kaal"
    },
    "level": "Intermediate",
    "emoji": "⏮️"
  },
  {
    "word": "work",
    "category": "Noun",
    "marathi": {
      "script": "काम",
      "transliteration": "kaam"
    },
    "level": "Intermediate",
    "emoji": "💼"
  },
  {
    "word": "play",
    "category": "Verb",
    "marathi": {
      "script": "खेळणे",
      "transliteration": "khelane"
    },
    "level": "Intermediate",
    "emoji": "🎮"
  },
  {
    "word": "read",
    "category": "Verb",
    "marathi": {
      "script": "वाचणे",
      "transliteration": "vachane"
    },
    "level": "Intermediate",
    "emoji": "📚"
  },
  {
    "word": "write",
    "category": "Verb",
    "marathi": {
      "script": "लिहिणे",
      "transliteration": "lihine"
    },
    "level": "Intermediate",
    "emoji": "✍️"
  },
  {
    "word": "run",
    "category": "Verb",
    "marathi": {
      "script": "धावणे",
      "transliteration": "dhaavane"
    },
    "level": "Intermediate",
    "emoji": "🏃"
  },
  {
    "word": "walk",
    "category": "Verb",
    "marathi": {
      "script": "चालणे",
      "transliteration": "chalane"
    },
    "level": "Intermediate",
    "emoji": "🚶"
  },
  {
    "word": "happy",
    "category": "Adjective",
    "marathi": {
      "script": "आनंदी",
      "transliteration": "anandi"
    },
    "level": "Intermediate",
    "emoji": "😊"
  },
  {
    "word": "sad",
    "category": "Adjective",
    "marathi": {
      "script": "दुःखी",
      "transliteration": "dukhi"
    },
    "level": "Intermediate",
    "emoji": "😢"
  },
  {
    "word": "fast",
    "category": "Adjective",
    "marathi": {
      "script": "जलद",
      "transliteration": "jalad"
    },
    "level": "Intermediate",
    "emoji": "⚡"
  },
  {
    "word": "slow",
    "category": "Adjective",
    "marathi": {
      "script": "हळू",
      "transliteration": "halu"
    },
    "level": "Intermediate",
    "emoji": "🐢"
  },
  {
    "word": "new",
    "category": "Adjective",
    "marathi": {
      "script": "नवीन",
      "transliteration": "naveen"
    },
    "level": "Intermediate",
    "emoji": "✨"
  },
  {
    "word": "because",
    "category": "Connector",
    "marathi": {
      "script": "कारण",
      "transliteration": "karan"
    },
    "level": "Advanced",
    "emoji": "🔗"
  },
  {
    "word": "but",
    "category": "Connector",
    "marathi": {
      "script": "पण",
      "transliteration": "pan"
    },
    "level": "Advanced",
    "emoji": "✋"
  },
  {
    "word": "and",
    "category": "Connector",
    "marathi": {
      "script": "आणि",
      "transliteration": "aani"
    },
    "level": "Advanced",
    "emoji": "➕"
  },
  {
    "word": "if",
    "category": "Connector",
    "marathi": {
      "script": "जर",
      "transliteration": "jar"
    },
    "level": "Advanced",
    "emoji": "❓"
  },
  {
    "word": "then",
    "category": "Connector",
    "marathi": {
      "script": "तर",
      "transliteration": "tar"
    },
    "level": "Advanced",
    "emoji": "➡️"
  },
  {
    "word": "before",
    "category": "Other",
    "marathi": {
      "script": "आधी",
      "transliteration": "aadhi"
    },
    "level": "Advanced",
    "emoji": "⏪"
  },
  {
    "word": "after",
    "category": "Other",
    "marathi": {
      "script": "नंतर",
      "transliteration": "nantar"
    },
    "level": "Advanced",
    "emoji": "⏩"
  },
  {
    "word": "always",
    "category": "Other",
    "marathi": {
      "script": "नेहमी",
      "transliteration": "nehmi"
    },
    "level": "Advanced",
    "emoji": "🔄"
  },
  {
    "word": "sometimes",
    "category": "Other",
    "marathi": {
      "script": "कधी कधी",
      "transliteration": "kadhi kadhi"
    },
    "level": "Advanced",
    "emoji": "⏳"
  },
  {
    "word": "never",
    "category": "Other",
    "marathi": {
      "script": "कधीच नाही",
      "transliteration": "kadhich nahi"
    },
    "level": "Advanced",
    "emoji": "🚫"
  },
  {
    "word": "think",
    "category": "Verb",
    "marathi": {
      "script": "विचार करणे",
      "transliteration": "vichar karane"
    },
    "level": "Advanced",
    "emoji": "🤔"
  },
  {
    "word": "know",
    "category": "Verb",
    "marathi": {
      "script": "माहित असणे",
      "transliteration": "mahiti asane"
    },
    "level": "Advanced",
    "emoji": "🧠"
  },
  {
    "word": "understand",
    "category": "Verb",
    "marathi": {
      "script": "समजणे",
      "transliteration": "samajane"
    },
    "level": "Advanced",
    "emoji": "💡"
  },
  {
    "word": "important",
    "category": "Adjective",
    "marathi": {
      "script": "महत्त्वाचे",
      "transliteration": "mahatvache"
    },
    "level": "Advanced",
    "emoji": "❗"
  },
  {
    "word": "different",
    "category": "Adjective",
    "marathi": {
      "script": "वेगळे",
      "transliteration": "vegale"
    },
    "level": "Advanced",
    "emoji": "🔀"
  },
  {
    "word": "experience",
    "category": "Noun",
    "marathi": {
      "script": "अनुभव",
      "transliteration": "anubhav"
    },
    "level": "Advanced",
    "emoji": "🌟"
  },
  {
    "word": "decision",
    "category": "Noun",
    "marathi": {
      "script": "निर्णय",
      "transliteration": "nirnay"
    },
    "level": "Advanced",
    "emoji": "⚖️"
  },
  {
    "word": "problem",
    "category": "Noun",
    "marathi": {
      "script": "समस्या",
      "transliteration": "samasya"
    },
    "level": "Advanced",
    "emoji": "🧩"
  },
  {
    "word": "solution",
    "category": "Noun",
    "marathi": {
      "script": "उपाय",
      "transliteration": "upaay"
    },
    "level": "Advanced",
    "emoji": "🔑"
  },
  {
    "word": "improve",
    "category": "Verb",
    "marathi": {
      "script": "सुधारणे",
      "transliteration": "sudharane"
    },
    "level": "Advanced",
    "emoji": "📈"
  },
  {
    "word": "create",
    "category": "Verb",
    "marathi": {
      "script": "निर्माण करणे",
      "transliteration": "nirman karane"
    },
    "level": "Advanced",
    "emoji": "🎨"
  },
  {
    "word": "develop",
    "category": "Verb",
    "marathi": {
      "script": "विकास करणे",
      "transliteration": "vikas karane"
    },
    "level": "Advanced",
    "emoji": "🏗️"
  },
  {
    "word": "possible",
    "category": "Adjective",
    "marathi": {
      "script": "शक्य",
      "transliteration": "shakya"
    },
    "level": "Advanced",
    "emoji": "✅"
  },
  {
    "word": "necessary",
    "category": "Adjective",
    "marathi": {
      "script": "आवश्यक",
      "transliteration": "aavashyak"
    },
    "level": "Advanced",
    "emoji": "📌"
  },
  {
    "word": "difficult",
    "category": "Adjective",
    "marathi": {
      "script": "कठीण",
      "transliteration": "kathin"
    },
    "level": "Advanced",
    "emoji": "🧗"
  }
]